sssg/__init__.py
sssg/__main__.py
sssg/argument_parser_builder.py
sssg/generator.py
sssg/schemas.py
sssg-0.0.4.dist-info/LICENSE
sssg-0.0.4.dist-info/METADATA
sssg-0.0.4.dist-info/WHEEL
sssg-0.0.4.dist-info/top_level.txt
sssg-0.0.4.dist-info/RECORD
